ds_example_plugin/__init__.py
ds_example_plugin/ds_example_plugin.py
ds_example_plugin-1.dist-info/LICENSE
ds_example_plugin-1.dist-info/METADATA
ds_example_plugin-1.dist-info/WHEEL
ds_example_plugin-1.dist-info/top_level.txt
ds_example_plugin-1.dist-info/RECORD
