Metadata-Version: 2.1
Name: ds-example-plugin
Version: 1
Summary: Example plugin for data_slicer`s PIT.
Home-page: https://github.com/kuadrat/ds_example_plugin.git
Author: Kevin Kramer
Author-email: kevin.kramer@uzh.ch
License: UNKNOWN
Platform: UNKNOWN
Classifier: Programming Language :: Python :: 3
Classifier: License :: OSI Approved :: MIT License
Classifier: Operating System :: OS Independent
Requires-Dist: data-slicer (>=0.0.12)
Requires-Dist: scipy (>=1.3.3)
